ADTdq/__init__.py
ADTdq/supporting/Message_Corrector_Key.xlsx
ADTdq/supporting/NSSP_Element_Reader.xlsx
ADTdq/supporting/NSSP_Validity_Reader.xlsx
ADTdq/supporting/NSSP_tryme.xlsx
ADTdq-1.1.2.dist-info/METADATA
ADTdq-1.1.2.dist-info/WHEEL
ADTdq-1.1.2.dist-info/top_level.txt
ADTdq-1.1.2.dist-info/RECORD
