Metadata-Version: 2.1
Name: ADTdq
Version: 1.1.2
Summary: A package designed to improve HL7 ADT Data Quality reporting in the field of public health informatics.
Home-page: https://github.com/pjgibson25/ADTdq
Author: PJ Gibson
Author-email: Peter.Gibson@doh.wa.gov
License: UNKNOWN
Platform: UNKNOWN
Classifier: Programming Language :: Python :: 3
Classifier: License :: OSI Approved :: MIT License
Classifier: Operating System :: OS Independent
Requires-Python: >=3.6
